{"name":"Collection Date","id":"modify-order;collection-date","testSteps":[{"number":1,"description":"1: Collection Date ({labNo\u003d20231099040004863, date\u003d09-02/2019, validation\u003dRejects incorect Format not in DD/MM/YYYY})","duration":11398,"startTime":"2023-07-17T15:34:33.136Z[Etc/UTC]","result":"SUCCESS","precondition":false,"level":0,"lineNumber":135,"children":[{"number":2,"description":"Given User Logs in to Home Page and goes to Modify Order Page","duration":5157,"startTime":"2023-07-17T15:34:33.679Z[Etc/UTC]","result":"SUCCESS","precondition":false,"level":1},{"number":3,"description":"And User Search by lab number \"20231099040004863\" from previous testing steps on the Modify Oder Page","duration":3094,"startTime":"2023-07-17T15:34:38.836Z[Etc/UTC]","result":"SUCCESS","precondition":false,"level":1},{"number":4,"description":"When User Enters Collection Date \"09-02/2019\" on the Modify Oder Page","duration":2410,"startTime":"2023-07-17T15:34:41.931Z[Etc/UTC]","result":"SUCCESS","precondition":false,"level":1},{"number":5,"description":"Then Collection Date Field validates \"Rejects incorect Format not in DD/MM/YYYY\" the date format","duration":100,"startTime":"2023-07-17T15:34:44.342Z[Etc/UTC]","result":"SUCCESS","precondition":false,"level":1}]},{"number":6,"description":"2: Collection Date ({labNo\u003d20231099040004863, date\u003ddd/mm/yyy, validation\u003dRejects incorect Format not Numeric})","duration":11208,"startTime":"2023-07-17T15:34:44.569Z[Etc/UTC]","result":"SUCCESS","precondition":false,"level":0,"lineNumber":136,"children":[{"number":7,"description":"Given User Logs in to Home Page and goes to Modify Order Page","duration":5135,"startTime":"2023-07-17T15:34:45.131Z[Etc/UTC]","result":"SUCCESS","precondition":false,"level":1},{"number":8,"description":"And User Search by lab number \"20231099040004863\" from previous testing steps on the Modify Oder Page","duration":2933,"startTime":"2023-07-17T15:34:50.266Z[Etc/UTC]","result":"SUCCESS","precondition":false,"level":1},{"number":9,"description":"When User Enters Collection Date \"dd/mm/yyy\" on the Modify Oder Page","duration":2400,"startTime":"2023-07-17T15:34:53.199Z[Etc/UTC]","result":"SUCCESS","precondition":false,"level":1},{"number":10,"description":"Then Collection Date Field validates \"Rejects incorect Format not Numeric\" the date format","duration":98,"startTime":"2023-07-17T15:34:55.600Z[Etc/UTC]","result":"SUCCESS","precondition":false,"level":1}]},{"number":11,"description":"3: Collection Date ({labNo\u003d20231099040004863, date\u003d09/02/5000, validation\u003dRejects Future date})","duration":12894,"startTime":"2023-07-17T15:34:55.826Z[Etc/UTC]","result":"SUCCESS","precondition":false,"level":0,"lineNumber":137,"children":[{"number":12,"description":"Given User Logs in to Home Page and goes to Modify Order Page","duration":5034,"startTime":"2023-07-17T15:34:56.553Z[Etc/UTC]","result":"SUCCESS","precondition":false,"level":1},{"number":13,"description":"And User Search by lab number \"20231099040004863\" from previous testing steps on the Modify Oder Page","duration":3516,"startTime":"2023-07-17T15:35:01.588Z[Etc/UTC]","result":"SUCCESS","precondition":false,"level":1},{"number":14,"description":"When User Enters Collection Date \"09/02/5000\" on the Modify Oder Page","duration":2377,"startTime":"2023-07-17T15:35:05.104Z[Etc/UTC]","result":"SUCCESS","precondition":false,"level":1},{"number":15,"description":"Then Collection Date Field validates \"Rejects Future date\" the date format","duration":1161,"startTime":"2023-07-17T15:35:07.482Z[Etc/UTC]","result":"SUCCESS","precondition":false,"level":1}]},{"number":16,"description":"4: Collection Date ({labNo\u003d20231099040004863, date\u003d09/01/2020, validation\u003dAccepts correct Format in DD/MM/YYYY})","duration":12508,"startTime":"2023-07-17T15:35:08.755Z[Etc/UTC]","result":"SUCCESS","precondition":false,"level":0,"lineNumber":138,"children":[{"number":17,"description":"Given User Logs in to Home Page and goes to Modify Order Page","duration":5145,"startTime":"2023-07-17T15:35:09.325Z[Etc/UTC]","result":"SUCCESS","precondition":false,"level":1},{"number":18,"description":"And User Search by lab number \"20231099040004863\" from previous testing steps on the Modify Oder Page","duration":3211,"startTime":"2023-07-17T15:35:14.471Z[Etc/UTC]","result":"SUCCESS","precondition":false,"level":1},{"number":19,"description":"When User Enters Collection Date \"09/01/2020\" on the Modify Oder Page","duration":2411,"startTime":"2023-07-17T15:35:17.683Z[Etc/UTC]","result":"SUCCESS","precondition":false,"level":1},{"number":20,"description":"Then Collection Date Field validates \"Accepts correct Format in DD/MM/YYYY\" the date format","duration":1060,"startTime":"2023-07-17T15:35:20.095Z[Etc/UTC]","result":"SUCCESS","precondition":false,"level":1}]}],"userStory":{"id":"modify-order","storyName":"Modify Order","path":"openelis/modifyOrder.feature","type":"feature"},"featureTag":{"name":"Openelis/Modify Order","type":"feature","displayName":"Openelis/Modify Order"},"title":"Collection Date","description":"","backgroundTitle":"","backgroundDescription":"","tags":[{"name":"modifyOrder","type":"tag","displayName":"modifyOrder"}],"startTime":"2023-07-17T15:34:33.134Z[Etc/UTC]","duration":48130,"projectKey":"","isManualTestingUpToDate":false,"dataTable":{"headers":["labNo","date","validation"],"rows":[{"values":["20231099040004863","09-02/2019","Rejects incorect Format not in DD/MM/YYYY"],"lineNumber":135,"result":"SUCCESS"},{"values":["20231099040004863","dd/mm/yyy","Rejects incorect Format not Numeric"],"lineNumber":136,"result":"SUCCESS"},{"values":["20231099040004863","09/02/5000","Rejects Future date"],"lineNumber":137,"result":"SUCCESS"},{"values":["20231099040004863","09/01/2020","Accepts correct Format in DD/MM/YYYY"],"lineNumber":138,"result":"SUCCESS"}],"predefinedRows":true,"scenarioOutline":"And User Search by lab number \"\u003clabNo\u003e\" from previous testing steps on the Modify Oder Page\n\rWhen User Enters Collection Date \"\u003cdate\u003e\" on the Modify Oder Page\n\rThen Collection Date Field validates \"\u003cvalidation\u003e\" the date format\n\r","dataSetDescriptors":[{"startRow":0,"rowCount":0,"name":"","description":""}]},"manual":false,"testSource":"Cucumber","result":"SUCCESS","scenarioOutline":"And User Search by lab number \"\u003clabNo\u003e\" from previous testing steps on the Modify Oder Page\nWhen User Enters Collection Date \"\u003cdate\u003e\" on the Modify Oder Page\nThen Collection Date Field validates \"\u003cvalidation\u003e\" the date format"}