{"name":"Patient Search","id":"patient-entry;patient-search","testSteps":[{"number":1,"description":"1: Patient Search ({lastName\u003dmusa, firstName\u003dmuranga, patientId\u003dug015, subjectNumber\u003doe015, labNo\u003d20230000000004217})","duration":17507,"startTime":"2023-06-26T18:30:22.281Z[Etc/UTC]","exception":{"errorType":"org.openqa.selenium.NoSuchElementException","message":"no such element: Unable to locate element: {\"method\":\"xpath\",\"selector\":\"//input[@value\u003d\u0027New Patient\u0027]\"}\n  (Session info: chrome\u003d114.0.5735.133)\nFor documentation on this error, please visit: https://www.seleniumhq.org/exceptions/no_such_element.html\nBuild info: version: \u00273.141.59\u0027, revision: \u0027e82be7d358\u0027, time: \u00272018-11-14T08:17:03\u0027\nSystem info: host: \u0027fv-az592-477\u0027, ip: \u002710.1.1.27\u0027, os.name: \u0027Linux\u0027, os.arch: \u0027amd64\u0027, os.version: \u00275.15.0-1040-azure\u0027, java.version: \u00271.8.0_372\u0027\nDriver info: org.openqa.selenium.remote.RemoteWebDriver\nCapabilities {acceptInsecureCerts: false, browserName: chrome, browserVersion: 114.0.5735.133, chrome: {chromedriverVersion: 114.0.5735.90 (386bc09e8f4f..., userDataDir: /tmp/.com.google.Chrome.dX4L60}, goog:chromeOptions: {debuggerAddress: localhost:46307}, javascriptEnabled: true, networkConnectionEnabled: false, pageLoadStrategy: normal, platform: LINUX, platformName: LINUX, proxy: Proxy(), se:bidiEnabled: false, se:cdp: ws://172.18.0.2:4444/sessio..., se:cdpVersion: 114.0.5735.133, se:vnc: ws://172.18.0.2:4444/sessio..., se:vncEnabled: true, se:vncLocalAddress: ws://172.18.0.2:7900, setWindowRect: true, strictFileInteractability: false, timeouts: {implicit: 0, pageLoad: 300000, script: 30000}, unhandledPromptBehavior: dismiss and notify, webauthn:extension:credBlob: true, webauthn:extension:largeBlob: true, webauthn:extension:minPinLength: true, webauthn:extension:prf: true, webauthn:virtualAuthenticators: true}\nSession ID: c27c1b7c3f638b4c497cab6018d693c5\n*** Element info: {Using\u003dxpath, value\u003d//input[@value\u003d\u0027New Patient\u0027]}\nFor documentation on this error, please visit: https://www.seleniumhq.org/exceptions/no_such_element.html\nBuild info: version: \u00273.141.59\u0027, revision: \u0027e82be7d358\u0027, time: \u00272018-11-14T08:17:03\u0027\nSystem info: host: \u0027fv-az592-477\u0027, ip: \u002710.1.1.27\u0027, os.name: \u0027Linux\u0027, os.arch: \u0027amd64\u0027, os.version: \u00275.15.0-1040-azure\u0027, java.version: \u00271.8.0_372\u0027\nDriver info: driver.version: unknown","stackTrace":[{"declaringClass":"org.openelisglobal.qaframework.automation.page.Page","methodName":"findElement","fileName":"Page.java","lineNumber":188},{"declaringClass":"org.openelisglobal.qaframework.automation.page.Page","methodName":"clickOn","fileName":"Page.java","lineNumber":266},{"declaringClass":"org.openelisglobal.qaframework.automation.page.AddPatientPage","methodName":"clickNewPatientButton","fileName":"AddPatientPage.java","lineNumber":122},{"declaringClass":"org.openelisglobal.qaframework.automation.page.AddPatientPage","methodName":"innitialisePatientData","fileName":"AddPatientPage.java","lineNumber":364},{"declaringClass":"org.openelisglobal.qaframework.automation.PatientEntrySteps","methodName":"AddModifyPageAppears","fileName":"PatientEntrySteps.java","lineNumber":57},{"declaringClass":"io.cucumber.java.Invoker","methodName":"doInvoke","fileName":"Invoker.java","lineNumber":66},{"declaringClass":"io.cucumber.java.Invoker","methodName":"invoke","fileName":"Invoker.java","lineNumber":24},{"declaringClass":"io.cucumber.java.AbstractGlueDefinition","methodName":"invokeMethod","fileName":"AbstractGlueDefinition.java","lineNumber":47},{"declaringClass":"io.cucumber.java.JavaStepDefinition","methodName":"execute","fileName":"JavaStepDefinition.java","lineNumber":29},{"declaringClass":"io.cucumber.core.runner.CoreStepDefinition","methodName":"execute","fileName":"CoreStepDefinition.java","lineNumber":66},{"declaringClass":"io.cucumber.core.runner.PickleStepDefinitionMatch","methodName":"runStep","fileName":"PickleStepDefinitionMatch.java","lineNumber":63},{"declaringClass":"io.cucumber.core.runner.TestStep","methodName":"executeStep","fileName":"TestStep.java","lineNumber":92},{"declaringClass":"io.cucumber.core.runner.TestStep","methodName":"run","fileName":"TestStep.java","lineNumber":64},{"declaringClass":"io.cucumber.core.runner.PickleStepTestStep","methodName":"run","fileName":"PickleStepTestStep.java","lineNumber":51},{"declaringClass":"io.cucumber.core.runner.TestCase","methodName":"run","fileName":"TestCase.java","lineNumber":104},{"declaringClass":"io.cucumber.core.runner.Runner","methodName":"runPickle","fileName":"Runner.java","lineNumber":73},{"declaringClass":"io.cucumber.junit.FeatureRunner","methodName":"runChild","fileName":"FeatureRunner.java","lineNumber":135},{"declaringClass":"io.cucumber.junit.FeatureRunner","methodName":"runChild","fileName":"FeatureRunner.java","lineNumber":27},{"declaringClass":"io.cucumber.junit.CucumberSerenityRunner","methodName":"runChild","fileName":"CucumberSerenityRunner.java","lineNumber":258},{"declaringClass":"io.cucumber.junit.CucumberSerenityRunner","methodName":"runChild","fileName":"CucumberSerenityRunner.java","lineNumber":57}]},"result":"ERROR","precondition":false,"level":0,"lineNumber":29,"children":[{"number":2,"description":"Given User Vists Home Page and goes to Add Add|Modify Patient Page","duration":6806,"startTime":"2023-06-26T18:30:22.757Z[Etc/UTC]","result":"SUCCESS","precondition":false,"level":1},{"number":3,"description":"Then Add|Modify Patient page appears with search field","duration":10076,"startTime":"2023-06-26T18:30:29.563Z[Etc/UTC]","exception":{"errorType":"org.openqa.selenium.NoSuchElementException","message":"no such element: Unable to locate element: {\"method\":\"xpath\",\"selector\":\"//input[@value\u003d\u0027New Patient\u0027]\"}\n  (Session info: chrome\u003d114.0.5735.133)\nFor documentation on this error, please visit: https://www.seleniumhq.org/exceptions/no_such_element.html\nBuild info: version: \u00273.141.59\u0027, revision: \u0027e82be7d358\u0027, time: \u00272018-11-14T08:17:03\u0027\nSystem info: host: \u0027fv-az592-477\u0027, ip: \u002710.1.1.27\u0027, os.name: \u0027Linux\u0027, os.arch: \u0027amd64\u0027, os.version: \u00275.15.0-1040-azure\u0027, java.version: \u00271.8.0_372\u0027\nDriver info: org.openqa.selenium.remote.RemoteWebDriver\nCapabilities {acceptInsecureCerts: false, browserName: chrome, browserVersion: 114.0.5735.133, chrome: {chromedriverVersion: 114.0.5735.90 (386bc09e8f4f..., userDataDir: /tmp/.com.google.Chrome.dX4L60}, goog:chromeOptions: {debuggerAddress: localhost:46307}, javascriptEnabled: true, networkConnectionEnabled: false, pageLoadStrategy: normal, platform: LINUX, platformName: LINUX, proxy: Proxy(), se:bidiEnabled: false, se:cdp: ws://172.18.0.2:4444/sessio..., se:cdpVersion: 114.0.5735.133, se:vnc: ws://172.18.0.2:4444/sessio..., se:vncEnabled: true, se:vncLocalAddress: ws://172.18.0.2:7900, setWindowRect: true, strictFileInteractability: false, timeouts: {implicit: 0, pageLoad: 300000, script: 30000}, unhandledPromptBehavior: dismiss and notify, webauthn:extension:credBlob: true, webauthn:extension:largeBlob: true, webauthn:extension:minPinLength: true, webauthn:extension:prf: true, webauthn:virtualAuthenticators: true}\nSession ID: c27c1b7c3f638b4c497cab6018d693c5\n*** Element info: {Using\u003dxpath, value\u003d//input[@value\u003d\u0027New Patient\u0027]}\nFor documentation on this error, please visit: https://www.seleniumhq.org/exceptions/no_such_element.html\nBuild info: version: \u00273.141.59\u0027, revision: \u0027e82be7d358\u0027, time: \u00272018-11-14T08:17:03\u0027\nSystem info: host: \u0027fv-az592-477\u0027, ip: \u002710.1.1.27\u0027, os.name: \u0027Linux\u0027, os.arch: \u0027amd64\u0027, os.version: \u00275.15.0-1040-azure\u0027, java.version: \u00271.8.0_372\u0027\nDriver info: driver.version: unknown","stackTrace":[{"declaringClass":"org.openelisglobal.qaframework.automation.page.Page","methodName":"findElement","fileName":"Page.java","lineNumber":188},{"declaringClass":"org.openelisglobal.qaframework.automation.page.Page","methodName":"clickOn","fileName":"Page.java","lineNumber":266},{"declaringClass":"org.openelisglobal.qaframework.automation.page.AddPatientPage","methodName":"clickNewPatientButton","fileName":"AddPatientPage.java","lineNumber":122},{"declaringClass":"org.openelisglobal.qaframework.automation.page.AddPatientPage","methodName":"innitialisePatientData","fileName":"AddPatientPage.java","lineNumber":364},{"declaringClass":"org.openelisglobal.qaframework.automation.PatientEntrySteps","methodName":"AddModifyPageAppears","fileName":"PatientEntrySteps.java","lineNumber":57},{"declaringClass":"io.cucumber.java.Invoker","methodName":"doInvoke","fileName":"Invoker.java","lineNumber":66},{"declaringClass":"io.cucumber.java.Invoker","methodName":"invoke","fileName":"Invoker.java","lineNumber":24},{"declaringClass":"io.cucumber.java.AbstractGlueDefinition","methodName":"invokeMethod","fileName":"AbstractGlueDefinition.java","lineNumber":47},{"declaringClass":"io.cucumber.java.JavaStepDefinition","methodName":"execute","fileName":"JavaStepDefinition.java","lineNumber":29},{"declaringClass":"io.cucumber.core.runner.CoreStepDefinition","methodName":"execute","fileName":"CoreStepDefinition.java","lineNumber":66},{"declaringClass":"io.cucumber.core.runner.PickleStepDefinitionMatch","methodName":"runStep","fileName":"PickleStepDefinitionMatch.java","lineNumber":63},{"declaringClass":"io.cucumber.core.runner.TestStep","methodName":"executeStep","fileName":"TestStep.java","lineNumber":92},{"declaringClass":"io.cucumber.core.runner.TestStep","methodName":"run","fileName":"TestStep.java","lineNumber":64},{"declaringClass":"io.cucumber.core.runner.PickleStepTestStep","methodName":"run","fileName":"PickleStepTestStep.java","lineNumber":51},{"declaringClass":"io.cucumber.core.runner.TestCase","methodName":"run","fileName":"TestCase.java","lineNumber":104},{"declaringClass":"io.cucumber.core.runner.Runner","methodName":"runPickle","fileName":"Runner.java","lineNumber":73},{"declaringClass":"io.cucumber.junit.FeatureRunner","methodName":"runChild","fileName":"FeatureRunner.java","lineNumber":135},{"declaringClass":"io.cucumber.junit.FeatureRunner","methodName":"runChild","fileName":"FeatureRunner.java","lineNumber":27},{"declaringClass":"io.cucumber.junit.CucumberSerenityRunner","methodName":"runChild","fileName":"CucumberSerenityRunner.java","lineNumber":258},{"declaringClass":"io.cucumber.junit.CucumberSerenityRunner","methodName":"runChild","fileName":"CucumberSerenityRunner.java","lineNumber":57}]},"result":"ERROR","precondition":false,"level":1},{"number":4,"description":"And Search button deactivated until search criteria is selected and text entered in the text field","duration":1,"startTime":"2023-06-26T18:30:39.648Z[Etc/UTC]","result":"SKIPPED","precondition":false,"level":1},{"number":5,"description":"And Search text boxes display correct search criteria","duration":0,"startTime":"2023-06-26T18:30:39.650Z[Etc/UTC]","result":"SKIPPED","precondition":false,"level":1},{"number":6,"description":"When User enters known last name \"musa\" in text box","duration":1,"startTime":"2023-06-26T18:30:39.651Z[Etc/UTC]","result":"SKIPPED","precondition":false,"level":1},{"number":7,"description":"Then Search by Last name yields all patients with matching last name on Add Patient Page","duration":1,"startTime":"2023-06-26T18:30:39.652Z[Etc/UTC]","result":"SKIPPED","precondition":false,"level":1},{"number":8,"description":"When User enters known first name \"muranga\" in text box","duration":1,"startTime":"2023-06-26T18:30:39.653Z[Etc/UTC]","result":"SKIPPED","precondition":false,"level":1},{"number":9,"description":"Then Search by First name yields all patients with matching first name on Add Patient Page","duration":1,"startTime":"2023-06-26T18:30:39.654Z[Etc/UTC]","result":"SKIPPED","precondition":false,"level":1},{"number":10,"description":"When User enters known last name \"musa\" and first name \"muranga\"","duration":1,"startTime":"2023-06-26T18:30:39.655Z[Etc/UTC]","result":"SKIPPED","precondition":false,"level":1},{"number":11,"description":"Then Search by Last name and First name yields results for known matching names","duration":1,"startTime":"2023-06-26T18:30:39.656Z[Etc/UTC]","result":"SKIPPED","precondition":false,"level":1},{"number":12,"description":"When User Select Search by Last name \"musa\", First name \"muranga\" but omit the comma between the parts of the name.","duration":1,"startTime":"2023-06-26T18:30:39.658Z[Etc/UTC]","result":"SKIPPED","precondition":false,"level":1},{"number":13,"description":"When User enters known Patient national Identification Number \"ug015\"","duration":1,"startTime":"2023-06-26T18:30:39.661Z[Etc/UTC]","result":"SKIPPED","precondition":false,"level":1},{"number":14,"description":"Then Search by Patient national Identification Number yields results for known matching names","duration":1,"startTime":"2023-06-26T18:30:39.662Z[Etc/UTC]","result":"SKIPPED","precondition":false,"level":1},{"number":15,"description":"When User enters known Subject Number \"oe015\"","duration":1,"startTime":"2023-06-26T18:30:39.664Z[Etc/UTC]","result":"SKIPPED","precondition":false,"level":1},{"number":16,"description":"Then Search by Subject Number yields results for known matching names","duration":1,"startTime":"2023-06-26T18:30:39.665Z[Etc/UTC]","result":"SKIPPED","precondition":false,"level":1},{"number":17,"description":"Then Select Search by Lab No \"20230000000004217\"","duration":1,"startTime":"2023-06-26T18:30:39.666Z[Etc/UTC]","result":"SKIPPED","precondition":false,"level":1},{"number":18,"description":"When User Selects correct patient","duration":1,"startTime":"2023-06-26T18:30:39.667Z[Etc/UTC]","result":"SKIPPED","precondition":false,"level":1},{"number":19,"description":"Then Patient Information form populates with patient information","duration":2,"startTime":"2023-06-26T18:30:39.668Z[Etc/UTC]","result":"SKIPPED","precondition":false,"level":1},{"number":20,"description":"When User Clicks New Patient on the Add Patient Page","duration":4,"startTime":"2023-06-26T18:30:39.670Z[Etc/UTC]","result":"SKIPPED","precondition":false,"level":1},{"number":21,"description":"Then Patient Information form clears","duration":2,"startTime":"2023-06-26T18:30:39.674Z[Etc/UTC]","result":"SKIPPED","precondition":false,"level":1}]}],"userStory":{"id":"patient-entry","storyName":"Patient Entry","path":"openelis/patientEntry.feature","type":"feature"},"featureTag":{"name":"Openelis/Patient Entry","type":"feature","displayName":"Openelis/Patient Entry"},"title":"Patient Search","description":"","backgroundTitle":"","backgroundDescription":"","tags":[{"name":"patientEntry","type":"tag","displayName":"patientEntry"}],"startTime":"2023-06-26T18:30:22.280Z[Etc/UTC]","duration":17509,"testFailureCause":{"errorType":"org.openqa.selenium.NoSuchElementException","message":"no such element: Unable to locate element: {\"method\":\"xpath\",\"selector\":\"//input[@value\u003d\u0027New Patient\u0027]\"}\n  (Session info: chrome\u003d114.0.5735.133)\nFor documentation on this error, please visit: https://www.seleniumhq.org/exceptions/no_such_element.html\nBuild info: version: \u00273.141.59\u0027, revision: \u0027e82be7d358\u0027, time: \u00272018-11-14T08:17:03\u0027\nSystem info: host: \u0027fv-az592-477\u0027, ip: \u002710.1.1.27\u0027, os.name: \u0027Linux\u0027, os.arch: \u0027amd64\u0027, os.version: \u00275.15.0-1040-azure\u0027, java.version: \u00271.8.0_372\u0027\nDriver info: org.openqa.selenium.remote.RemoteWebDriver\nCapabilities {acceptInsecureCerts: false, browserName: chrome, browserVersion: 114.0.5735.133, chrome: {chromedriverVersion: 114.0.5735.90 (386bc09e8f4f..., userDataDir: /tmp/.com.google.Chrome.dX4L60}, goog:chromeOptions: {debuggerAddress: localhost:46307}, javascriptEnabled: true, networkConnectionEnabled: false, pageLoadStrategy: normal, platform: LINUX, platformName: LINUX, proxy: Proxy(), se:bidiEnabled: false, se:cdp: ws://172.18.0.2:4444/sessio..., se:cdpVersion: 114.0.5735.133, se:vnc: ws://172.18.0.2:4444/sessio..., se:vncEnabled: true, se:vncLocalAddress: ws://172.18.0.2:7900, setWindowRect: true, strictFileInteractability: false, timeouts: {implicit: 0, pageLoad: 300000, script: 30000}, unhandledPromptBehavior: dismiss and notify, webauthn:extension:credBlob: true, webauthn:extension:largeBlob: true, webauthn:extension:minPinLength: true, webauthn:extension:prf: true, webauthn:virtualAuthenticators: true}\nSession ID: c27c1b7c3f638b4c497cab6018d693c5\n*** Element info: {Using\u003dxpath, value\u003d//input[@value\u003d\u0027New Patient\u0027]}\nFor documentation on this error, please visit: https://www.seleniumhq.org/exceptions/no_such_element.html\nBuild info: version: \u00273.141.59\u0027, revision: \u0027e82be7d358\u0027, time: \u00272018-11-14T08:17:03\u0027\nSystem info: host: \u0027fv-az592-477\u0027, ip: \u002710.1.1.27\u0027, os.name: \u0027Linux\u0027, os.arch: \u0027amd64\u0027, os.version: \u00275.15.0-1040-azure\u0027, java.version: \u00271.8.0_372\u0027\nDriver info: driver.version: unknown","stackTrace":[{"declaringClass":"org.openelisglobal.qaframework.automation.page.Page","methodName":"findElement","fileName":"Page.java","lineNumber":188},{"declaringClass":"org.openelisglobal.qaframework.automation.page.Page","methodName":"clickOn","fileName":"Page.java","lineNumber":266},{"declaringClass":"org.openelisglobal.qaframework.automation.page.AddPatientPage","methodName":"clickNewPatientButton","fileName":"AddPatientPage.java","lineNumber":122},{"declaringClass":"org.openelisglobal.qaframework.automation.page.AddPatientPage","methodName":"innitialisePatientData","fileName":"AddPatientPage.java","lineNumber":364},{"declaringClass":"org.openelisglobal.qaframework.automation.PatientEntrySteps","methodName":"AddModifyPageAppears","fileName":"PatientEntrySteps.java","lineNumber":57},{"declaringClass":"io.cucumber.java.Invoker","methodName":"doInvoke","fileName":"Invoker.java","lineNumber":66},{"declaringClass":"io.cucumber.java.Invoker","methodName":"invoke","fileName":"Invoker.java","lineNumber":24},{"declaringClass":"io.cucumber.java.AbstractGlueDefinition","methodName":"invokeMethod","fileName":"AbstractGlueDefinition.java","lineNumber":47},{"declaringClass":"io.cucumber.java.JavaStepDefinition","methodName":"execute","fileName":"JavaStepDefinition.java","lineNumber":29},{"declaringClass":"io.cucumber.core.runner.CoreStepDefinition","methodName":"execute","fileName":"CoreStepDefinition.java","lineNumber":66},{"declaringClass":"io.cucumber.core.runner.PickleStepDefinitionMatch","methodName":"runStep","fileName":"PickleStepDefinitionMatch.java","lineNumber":63},{"declaringClass":"io.cucumber.core.runner.TestStep","methodName":"executeStep","fileName":"TestStep.java","lineNumber":92},{"declaringClass":"io.cucumber.core.runner.TestStep","methodName":"run","fileName":"TestStep.java","lineNumber":64},{"declaringClass":"io.cucumber.core.runner.PickleStepTestStep","methodName":"run","fileName":"PickleStepTestStep.java","lineNumber":51},{"declaringClass":"io.cucumber.core.runner.TestCase","methodName":"run","fileName":"TestCase.java","lineNumber":104},{"declaringClass":"io.cucumber.core.runner.Runner","methodName":"runPickle","fileName":"Runner.java","lineNumber":73},{"declaringClass":"io.cucumber.junit.FeatureRunner","methodName":"runChild","fileName":"FeatureRunner.java","lineNumber":135},{"declaringClass":"io.cucumber.junit.FeatureRunner","methodName":"runChild","fileName":"FeatureRunner.java","lineNumber":27},{"declaringClass":"io.cucumber.junit.CucumberSerenityRunner","methodName":"runChild","fileName":"CucumberSerenityRunner.java","lineNumber":258},{"declaringClass":"io.cucumber.junit.CucumberSerenityRunner","methodName":"runChild","fileName":"CucumberSerenityRunner.java","lineNumber":57}]},"testFailureClassname":"org.openqa.selenium.NoSuchElementException","testFailureMessage":"no such element: Unable to locate element: {\"method\":\"xpath\",\"selector\":\"//input[@value\u003d\u0027New Patient\u0027]\"}\n  (Session info: chrome\u003d114.0.5735.133)\nFor documentation on this error, please visit: https://www.seleniumhq.org/exceptions/no_such_element.html\nBuild info: version: \u00273.141.59\u0027, revision: \u0027e82be7d358\u0027, time: \u00272018-11-14T08:17:03\u0027\nSystem info: host: \u0027fv-az592-477\u0027, ip: \u002710.1.1.27\u0027, os.name: \u0027Linux\u0027, os.arch: \u0027amd64\u0027, os.version: \u00275.15.0-1040-azure\u0027, java.version: \u00271.8.0_372\u0027\nDriver info: org.openqa.selenium.remote.RemoteWebDriver\nCapabilities {acceptInsecureCerts: false, browserName: chrome, browserVersion: 114.0.5735.133, chrome: {chromedriverVersion: 114.0.5735.90 (386bc09e8f4f..., userDataDir: /tmp/.com.google.Chrome.dX4L60}, goog:chromeOptions: {debuggerAddress: localhost:46307}, javascriptEnabled: true, networkConnectionEnabled: false, pageLoadStrategy: normal, platform: LINUX, platformName: LINUX, proxy: Proxy(), se:bidiEnabled: false, se:cdp: ws://172.18.0.2:4444/sessio..., se:cdpVersion: 114.0.5735.133, se:vnc: ws://172.18.0.2:4444/sessio..., se:vncEnabled: true, se:vncLocalAddress: ws://172.18.0.2:7900, setWindowRect: true, strictFileInteractability: false, timeouts: {implicit: 0, pageLoad: 300000, script: 30000}, unhandledPromptBehavior: dismiss and notify, webauthn:extension:credBlob: true, webauthn:extension:largeBlob: true, webauthn:extension:minPinLength: true, webauthn:extension:prf: true, webauthn:virtualAuthenticators: true}\nSession ID: c27c1b7c3f638b4c497cab6018d693c5\n*** Element info: {Using\u003dxpath, value\u003d//input[@value\u003d\u0027New Patient\u0027]}\nFor documentation on this error, please visit: https://www.seleniumhq.org/exceptions/no_such_element.html\nBuild info: version: \u00273.141.59\u0027, revision: \u0027e82be7d358\u0027, time: \u00272018-11-14T08:17:03\u0027\nSystem info: host: \u0027fv-az592-477\u0027, ip: \u002710.1.1.27\u0027, os.name: \u0027Linux\u0027, os.arch: \u0027amd64\u0027, os.version: \u00275.15.0-1040-azure\u0027, java.version: \u00271.8.0_372\u0027\nDriver info: driver.version: unknown","testFailureSummary":"ERROR;org.openqa.selenium.NoSuchElementException;no such element: Unable to locate element: {\"method\":\"xpath\",\"selector\":\"//input[@value\u003d\u0027New Patient\u0027]\"}\n  (Session info: chrome\u003d114.0.5735.133)\nFor documentation on this error, please visit: https://www.seleniumhq.org/exceptions/no_such_element.html\nBuild info: version: \u00273.141.59\u0027, revision: \u0027e82be7d358\u0027, time: \u00272018-11-14T08:17:03\u0027\nSystem info: host: \u0027fv-az592-477\u0027, ip: \u002710.1.1.27\u0027, os.name: \u0027Linux\u0027, os.arch: \u0027amd64\u0027, os.version: \u00275.15.0-1040-azure\u0027, java.version: \u00271.8.0_372\u0027\nDriver info: org.openqa.selenium.remote.RemoteWebDriver\nCapabilities {acceptInsecureCerts: false, browserName: chrome, browserVersion: 114.0.5735.133, chrome: {chromedriverVersion: 114.0.5735.90 (386bc09e8f4f..., userDataDir: /tmp/.com.google.Chrome.dX4L60}, goog:chromeOptions: {debuggerAddress: localhost:46307}, javascriptEnabled: true, networkConnectionEnabled: false, pageLoadStrategy: normal, platform: LINUX, platformName: LINUX, proxy: Proxy(), se:bidiEnabled: false, se:cdp: ws://172.18.0.2:4444/sessio..., se:cdpVersion: 114.0.5735.133, se:vnc: ws://172.18.0.2:4444/sessio..., se:vncEnabled: true, se:vncLocalAddress: ws://172.18.0.2:7900, setWindowRect: true, strictFileInteractability: false, timeouts: {implicit: 0, pageLoad: 300000, script: 30000}, unhandledPromptBehavior: dismiss and notify, webauthn:extension:credBlob: true, webauthn:extension:largeBlob: true, webauthn:extension:minPinLength: true, webauthn:extension:prf: true, webauthn:virtualAuthenticators: true}\nSession ID: c27c1b7c3f638b4c497cab6018d693c5\n*** Element info: {Using\u003dxpath, value\u003d//input[@value\u003d\u0027New Patient\u0027]}\nFor documentation on this error, please visit: https://www.seleniumhq.org/exceptions/no_such_element.html\nBuild info: version: \u00273.141.59\u0027, revision: \u0027e82be7d358\u0027, time: \u00272018-11-14T08:17:03\u0027\nSystem info: host: \u0027fv-az592-477\u0027, ip: \u002710.1.1.27\u0027, os.name: \u0027Linux\u0027, os.arch: \u0027amd64\u0027, os.version: \u00275.15.0-1040-azure\u0027, java.version: \u00271.8.0_372\u0027\nDriver info: driver.version: unknown;Page.java","projectKey":"","annotatedResult":"ERROR","isManualTestingUpToDate":false,"dataTable":{"headers":["lastName","firstName","patientId","subjectNumber","labNo"],"rows":[{"values":["musa","muranga","ug015","oe015","20230000000004217"],"lineNumber":29,"result":"ERROR"}],"predefinedRows":true,"scenarioOutline":"Then Add|Modify Patient page appears with search field\n\rAnd Search button deactivated until search criteria is selected and text entered in the text field\n\rAnd Search text boxes display correct search criteria\n\rWhen User enters known last name \"\u003clastName\u003e\" in text box\n\rThen Search by Last name yields all patients with matching last name on Add Patient Page\n\rWhen User enters known first name \"\u003cfirstName\u003e\" in text box\n\rThen Search by First name yields all patients with matching first name on Add Patient Page\n\rWhen User enters known last name \"\u003clastName\u003e\" and first name \"\u003cfirstName\u003e\"\n\rThen Search by Last name and First name yields results for known matching names\n\rWhen User Select Search by Last name \"\u003clastName\u003e\", First name \"\u003cfirstName\u003e\" but omit the comma between the parts of the name.\n\rWhen User enters known Patient national Identification Number \"\u003cpatientId\u003e\"\n\rThen Search by Patient national Identification Number yields results for known matching names\n\rWhen User enters known Subject Number \"\u003csubjectNumber\u003e\"\n\rThen Search by Subject Number yields results for known matching names\n\rThen Select Search by Lab No \"\u003clabNo\u003e\"\n\rWhen User Selects correct patient\n\rThen Patient Information form populates with patient information\n\rWhen User Clicks New Patient on the Add Patient Page\n\rThen Patient Information form clears\n\r","dataSetDescriptors":[{"startRow":0,"rowCount":0,"name":"","description":""}]},"manual":false,"testSource":"Cucumber","result":"ERROR","scenarioOutline":"Then Add|Modify Patient page appears with search field\nAnd Search button deactivated until search criteria is selected and text entered in the text field\nAnd Search text boxes display correct search criteria\nWhen User enters known last name \"\u003clastName\u003e\" in text box\nThen Search by Last name yields all patients with matching last name on Add Patient Page\nWhen User enters known first name \"\u003cfirstName\u003e\" in text box\nThen Search by First name yields all patients with matching first name on Add Patient Page\nWhen User enters known last name \"\u003clastName\u003e\" and first name \"\u003cfirstName\u003e\"\nThen Search by Last name and First name yields results for known matching names\nWhen User Select Search by Last name \"\u003clastName\u003e\", First name \"\u003cfirstName\u003e\" but omit the comma between the parts of the name.\nWhen User enters known Patient national Identification Number \"\u003cpatientId\u003e\"\nThen Search by Patient national Identification Number yields results for known matching names\nWhen User enters known Subject Number \"\u003csubjectNumber\u003e\"\nThen Search by Subject Number yields results for known matching names\nThen Select Search by Lab No \"\u003clabNo\u003e\"\nWhen User Selects correct patient\nThen Patient Information form populates with patient information\nWhen User Clicks New Patient on the Add Patient Page\nThen Patient Information form clears"}