{"name":"Patient Report With Partial result reported","id":"patient-report;patient-report-with-partial-result-reported","testSteps":[{"number":1,"description":"Given User Vists Home Page and goes to Add Order Page","duration":7996,"startTime":"2023-03-17T00:41:25.606Z[Etc/UTC]","result":"SUCCESS","precondition":false,"level":0},{"number":2,"description":"When User Goes to Modify Order for the same order from Use Case 1 and cancel one test","duration":18233,"startTime":"2023-03-17T00:41:33.602Z[Etc/UTC]","result":"SUCCESS","precondition":false,"level":0},{"number":3,"description":"And User Looks up Results Entry for the same order, Complete some but not all results","duration":16089,"startTime":"2023-03-17T00:41:51.835Z[Etc/UTC]","result":"SUCCESS","precondition":false,"level":0},{"number":4,"description":"And User Validates all results but one for this order, Send the last result back to Retest","duration":15178,"startTime":"2023-03-17T00:42:07.924Z[Etc/UTC]","result":"SUCCESS","precondition":false,"level":0},{"number":5,"description":"And User Generates the Patient Report for this order with Results","duration":2183,"startTime":"2023-03-17T00:42:23.103Z[Etc/UTC]","result":"SUCCESS","precondition":false,"level":0},{"number":6,"description":"Then Verify the generated Report","duration":383,"startTime":"2023-03-17T00:42:25.286Z[Etc/UTC]","result":"SUCCESS","precondition":false,"level":0}],"userStory":{"id":"patient-report","storyName":"Patient Report","path":"openelis/patientReport.feature","type":"feature"},"featureTag":{"name":"Openelis/Patient Report","type":"feature","displayName":"Openelis/Patient Report"},"title":"Patient Report With Partial result reported","description":"","backgroundTitle":"","backgroundDescription":"","tags":[{"name":"report","type":"tag","displayName":"report"}],"startTime":"2023-03-17T00:41:25.049Z[Etc/UTC]","duration":60708,"projectKey":"","isManualTestingUpToDate":false,"manual":false,"testSource":"Cucumber","result":"SUCCESS"}