{"name":"Available Test Information","id":"modify-order;available-test-information","testSteps":[{"number":1,"description":"1: Available Test Information ({labNo\u003d20231099040004863})","duration":10507,"startTime":"2023-03-21T14:27:50.638Z[Etc/UTC]","result":"SUCCESS","precondition":false,"level":0,"lineNumber":104,"children":[{"number":2,"description":"Given User Logs in to Home Page and goes to Modify Order Page","duration":5843,"startTime":"2023-03-21T14:27:51.150Z[Etc/UTC]","result":"SUCCESS","precondition":false,"level":1},{"number":3,"description":"When User Search by lab number \"20231099040004863\" from previous testing steps on the Modify Oder Page","duration":3373,"startTime":"2023-03-21T14:27:56.993Z[Etc/UTC]","result":"SUCCESS","precondition":false,"level":1},{"number":4,"description":"Then Table headers are correct Under Available Tests","duration":330,"startTime":"2023-03-21T14:28:00.366Z[Etc/UTC]","result":"SUCCESS","precondition":false,"level":1},{"number":5,"description":"When User Check box next to  several tests","duration":104,"startTime":"2023-03-21T14:28:00.697Z[Etc/UTC]","result":"SUCCESS","precondition":false,"level":1},{"number":6,"description":"Then Assign test Check boxes stick","duration":90,"startTime":"2023-03-21T14:28:00.801Z[Etc/UTC]","result":"SUCCESS","precondition":false,"level":1},{"number":7,"description":"When User unCheck box next to  several tests","duration":81,"startTime":"2023-03-21T14:28:00.892Z[Etc/UTC]","result":"SUCCESS","precondition":false,"level":1},{"number":8,"description":"Then Assign test Check boxes will uncheck","duration":67,"startTime":"2023-03-21T14:28:00.974Z[Etc/UTC]","result":"SUCCESS","precondition":false,"level":1}]}],"userStory":{"id":"modify-order","storyName":"Modify Order","path":"openelis/modifyOrder.feature","type":"feature"},"featureTag":{"name":"Openelis/Modify Order","type":"feature","displayName":"Openelis/Modify Order"},"title":"Available Test Information","description":"","backgroundTitle":"","backgroundDescription":"","tags":[{"name":"modifyOrder","type":"tag","displayName":"modifyOrder"}],"startTime":"2023-03-21T14:27:50.636Z[Etc/UTC]","duration":10510,"projectKey":"","isManualTestingUpToDate":false,"dataTable":{"headers":["labNo"],"rows":[{"values":["20231099040004863"],"lineNumber":104,"result":"SUCCESS"}],"predefinedRows":true,"scenarioOutline":"When User Search by lab number \"\u003clabNo\u003e\" from previous testing steps on the Modify Oder Page\n\rThen Table headers are correct Under Available Tests\n\rWhen User Check box next to  several tests\n\rThen Assign test Check boxes stick\n\rWhen User unCheck box next to  several tests\n\rThen Assign test Check boxes will uncheck\n\r","dataSetDescriptors":[{"startRow":0,"rowCount":0,"name":"","description":""}]},"manual":false,"testSource":"Cucumber","result":"SUCCESS","scenarioOutline":"When User Search by lab number \"\u003clabNo\u003e\" from previous testing steps on the Modify Oder Page\nThen Table headers are correct Under Available Tests\nWhen User Check box next to  several tests\nThen Assign test Check boxes stick\nWhen User unCheck box next to  several tests\nThen Assign test Check boxes will uncheck"}