{"name":"Patient Information","id":"add-order;patient-information","testSteps":[{"number":1,"description":"1: Patient Information ({subjectNumber\u003d202307D9P, nationalId\u003d201507D35, pLastName\u003dAliou, pFirstName\u003dSADIO, cLastName\u003dmusa, cFirstName\u003dmutes, cEmail\u003dwrongEmail, cPhone\u003d+23063458788, street\u003dNew York city, street 3334, commune\u003dGrand yoff, town\u003dDakar, pPhone\u003dff223377, pEmail\u003dwrongEmail, dateOfBirth\u003d09/02/dd, nationality\u003dAmerican, age\u003d20, status\u003dinvalid})","duration":73540,"startTime":"2023-05-15T23:27:35.600Z[Etc/UTC]","result":"SUCCESS","precondition":false,"level":0,"lineNumber":203,"children":[{"number":2,"description":"Given User logs in and visits Home page","duration":6121,"startTime":"2023-05-15T23:27:36.078Z[Etc/UTC]","result":"SUCCESS","precondition":false,"level":1},{"number":3,"description":"And User clicks add order and goes to Add order Page","duration":2126,"startTime":"2023-05-15T23:27:42.200Z[Etc/UTC]","result":"SUCCESS","precondition":false,"level":1},{"number":4,"description":"When User Expands Patient information form by clicking the + button next to Patient","duration":119,"startTime":"2023-05-15T23:27:44.327Z[Etc/UTC]","result":"SUCCESS","precondition":false,"level":1},{"number":5,"description":"And User Clicks New Patient Button","duration":8778,"startTime":"2023-05-15T23:27:44.447Z[Etc/UTC]","result":"SUCCESS","precondition":false,"level":1},{"number":6,"description":"And User Enters Subject Number \"202307D9P\"","duration":1241,"startTime":"2023-05-15T23:27:53.226Z[Etc/UTC]","result":"SUCCESS","precondition":false,"level":1},{"number":7,"description":"And User Enters National ID \"201507D35\"","duration":1212,"startTime":"2023-05-15T23:27:54.468Z[Etc/UTC]","result":"SUCCESS","precondition":false,"level":1},{"number":8,"description":"And User Enters Patient Last Name \"Aliou\"","duration":1230,"startTime":"2023-05-15T23:27:55.681Z[Etc/UTC]","result":"SUCCESS","precondition":false,"level":1},{"number":9,"description":"And User Enters Patient First Name \"SADIO\"","duration":1228,"startTime":"2023-05-15T23:27:56.911Z[Etc/UTC]","result":"SUCCESS","precondition":false,"level":1},{"number":10,"description":"And User Enters Contact Last Name \"musa\"","duration":1183,"startTime":"2023-05-15T23:27:58.140Z[Etc/UTC]","result":"SUCCESS","precondition":false,"level":1},{"number":11,"description":"And User Enters Contact First Name \"mutes\"","duration":1234,"startTime":"2023-05-15T23:27:59.324Z[Etc/UTC]","result":"SUCCESS","precondition":false,"level":1},{"number":12,"description":"And User Enters Contact Email \"wrongEmail\"","duration":1240,"startTime":"2023-05-15T23:28:00.559Z[Etc/UTC]","result":"SUCCESS","precondition":false,"level":1},{"number":13,"description":"Then Field validates \"invalid\" Contact Email","duration":1240,"startTime":"2023-05-15T23:28:01.800Z[Etc/UTC]","result":"SUCCESS","precondition":false,"level":1},{"number":14,"description":"And User Enters Contact Phone \"+23063458788\"","duration":1227,"startTime":"2023-05-15T23:28:03.040Z[Etc/UTC]","result":"SUCCESS","precondition":false,"level":1},{"number":15,"description":"And User Enters Patient Street \"New York city, street 3334\"","duration":1225,"startTime":"2023-05-15T23:28:04.268Z[Etc/UTC]","result":"SUCCESS","precondition":false,"level":1},{"number":16,"description":"And User Enters Patient Commune \"Grand yoff\"","duration":1254,"startTime":"2023-05-15T23:28:05.494Z[Etc/UTC]","result":"SUCCESS","precondition":false,"level":1},{"number":17,"description":"And User Enters Patient Town \"Dakar\"","duration":1176,"startTime":"2023-05-15T23:28:06.748Z[Etc/UTC]","result":"SUCCESS","precondition":false,"level":1},{"number":18,"description":"And User Enters Patient Phone \"ff223377\"","duration":1190,"startTime":"2023-05-15T23:28:07.925Z[Etc/UTC]","result":"SUCCESS","precondition":false,"level":1},{"number":19,"description":"Then Field validates \"invalid\" Patient Phone","duration":2369,"startTime":"2023-05-15T23:28:09.116Z[Etc/UTC]","result":"SUCCESS","precondition":false,"level":1},{"number":20,"description":"And User Enters Patient Email \"wrongEmail\"","duration":10050,"startTime":"2023-05-15T23:28:11.486Z[Etc/UTC]","result":"SUCCESS","precondition":false,"level":1},{"number":21,"description":"Then Field validates \"invalid\" Patient Email","duration":10025,"startTime":"2023-05-15T23:28:21.537Z[Etc/UTC]","result":"SUCCESS","precondition":false,"level":1},{"number":22,"description":"And User Selects Patient Health Region","duration":290,"startTime":"2023-05-15T23:28:31.563Z[Etc/UTC]","result":"SUCCESS","precondition":false,"level":1},{"number":23,"description":"And User Selects Patient Health District from the drop down","duration":306,"startTime":"2023-05-15T23:28:31.854Z[Etc/UTC]","result":"SUCCESS","precondition":false,"level":1},{"number":24,"description":"And User Enters Patient Date of Birth \"09/02/dd\"","duration":1256,"startTime":"2023-05-15T23:28:32.161Z[Etc/UTC]","result":"SUCCESS","precondition":false,"level":1},{"number":25,"description":"Then Field validates \"invalid\" Patient Date Of Birth","duration":1211,"startTime":"2023-05-15T23:28:33.418Z[Etc/UTC]","result":"SUCCESS","precondition":false,"level":1},{"number":26,"description":"When User Enters Patient Date of Birth in future","duration":1202,"startTime":"2023-05-15T23:28:34.629Z[Etc/UTC]","result":"SUCCESS","precondition":false,"level":1},{"number":27,"description":"Then Alert appears if Date is in the Future","duration":1247,"startTime":"2023-05-15T23:28:35.831Z[Etc/UTC]","result":"SUCCESS","precondition":false,"level":1},{"number":28,"description":"When Date of Birth is left blank and Age \"20\" is filled","duration":1309,"startTime":"2023-05-15T23:28:37.079Z[Etc/UTC]","result":"SUCCESS","precondition":false,"level":1},{"number":29,"description":"Then Field generates Date of Birth with correct year for the Age \"20\"","duration":1200,"startTime":"2023-05-15T23:28:38.389Z[Etc/UTC]","result":"SUCCESS","precondition":false,"level":1},{"number":30,"description":"And Alert Appears if Age entered is -1 , 100 and \u003e100","duration":7628,"startTime":"2023-05-15T23:28:39.590Z[Etc/UTC]","result":"SUCCESS","precondition":false,"level":1},{"number":31,"description":"And User Selects Patient Gender","duration":189,"startTime":"2023-05-15T23:28:47.218Z[Etc/UTC]","result":"SUCCESS","precondition":false,"level":1},{"number":32,"description":"And User Selects Patient Education","duration":244,"startTime":"2023-05-15T23:28:47.408Z[Etc/UTC]","result":"SUCCESS","precondition":false,"level":1},{"number":33,"description":"And User Selects Patient Marital Status","duration":191,"startTime":"2023-05-15T23:28:47.653Z[Etc/UTC]","result":"SUCCESS","precondition":false,"level":1},{"number":34,"description":"And User Enters Patient Other Nationality \"American\"","duration":1192,"startTime":"2023-05-15T23:28:47.845Z[Etc/UTC]","result":"SUCCESS","precondition":false,"level":1}]},{"number":35,"description":"2: Patient Information ({subjectNumber\u003d202307D9P, nationalId\u003d201507D35, pLastName\u003dAliou, pFirstName\u003dSADIO, cLastName\u003dmusa, cFirstName\u003dmutes, cEmail\u003dcontact@gmail.com, cPhone\u003d+23063458788, street\u003dNew York city, street 3334, commune\u003dGrand yoff, town\u003dDakar, pPhone\u003d+23063458788, pEmail\u003dpat@gmail.com, dateOfBirth\u003d09/02/2019, nationality\u003dAmerican, age\u003d20, status\u003dvalid})","duration":73314,"startTime":"2023-05-15T23:28:49.176Z[Etc/UTC]","result":"SUCCESS","precondition":false,"level":0,"lineNumber":204,"children":[{"number":36,"description":"Given User logs in and visits Home page","duration":5964,"startTime":"2023-05-15T23:28:49.656Z[Etc/UTC]","result":"SUCCESS","precondition":false,"level":1},{"number":37,"description":"And User clicks add order and goes to Add order Page","duration":2336,"startTime":"2023-05-15T23:28:55.621Z[Etc/UTC]","result":"SUCCESS","precondition":false,"level":1},{"number":38,"description":"When User Expands Patient information form by clicking the + button next to Patient","duration":59,"startTime":"2023-05-15T23:28:57.958Z[Etc/UTC]","result":"SUCCESS","precondition":false,"level":1},{"number":39,"description":"And User Clicks New Patient Button","duration":8781,"startTime":"2023-05-15T23:28:58.018Z[Etc/UTC]","result":"SUCCESS","precondition":false,"level":1},{"number":40,"description":"And User Enters Subject Number \"202307D9P\"","duration":1298,"startTime":"2023-05-15T23:29:06.800Z[Etc/UTC]","result":"SUCCESS","precondition":false,"level":1},{"number":41,"description":"And User Enters National ID \"201507D35\"","duration":1197,"startTime":"2023-05-15T23:29:08.099Z[Etc/UTC]","result":"SUCCESS","precondition":false,"level":1},{"number":42,"description":"And User Enters Patient Last Name \"Aliou\"","duration":1196,"startTime":"2023-05-15T23:29:09.296Z[Etc/UTC]","result":"SUCCESS","precondition":false,"level":1},{"number":43,"description":"And User Enters Patient First Name \"SADIO\"","duration":1182,"startTime":"2023-05-15T23:29:10.492Z[Etc/UTC]","result":"SUCCESS","precondition":false,"level":1},{"number":44,"description":"And User Enters Contact Last Name \"musa\"","duration":1179,"startTime":"2023-05-15T23:29:11.675Z[Etc/UTC]","result":"SUCCESS","precondition":false,"level":1},{"number":45,"description":"And User Enters Contact First Name \"mutes\"","duration":1187,"startTime":"2023-05-15T23:29:12.855Z[Etc/UTC]","result":"SUCCESS","precondition":false,"level":1},{"number":46,"description":"And User Enters Contact Email \"contact@gmail.com\"","duration":1192,"startTime":"2023-05-15T23:29:14.043Z[Etc/UTC]","result":"SUCCESS","precondition":false,"level":1},{"number":47,"description":"Then Field validates \"valid\" Contact Email","duration":1201,"startTime":"2023-05-15T23:29:15.236Z[Etc/UTC]","result":"SUCCESS","precondition":false,"level":1},{"number":48,"description":"And User Enters Contact Phone \"+23063458788\"","duration":1241,"startTime":"2023-05-15T23:29:16.438Z[Etc/UTC]","result":"SUCCESS","precondition":false,"level":1},{"number":49,"description":"And User Enters Patient Street \"New York city, street 3334\"","duration":1284,"startTime":"2023-05-15T23:29:17.679Z[Etc/UTC]","result":"SUCCESS","precondition":false,"level":1},{"number":50,"description":"And User Enters Patient Commune \"Grand yoff\"","duration":1221,"startTime":"2023-05-15T23:29:18.964Z[Etc/UTC]","result":"SUCCESS","precondition":false,"level":1},{"number":51,"description":"And User Enters Patient Town \"Dakar\"","duration":1220,"startTime":"2023-05-15T23:29:20.186Z[Etc/UTC]","result":"SUCCESS","precondition":false,"level":1},{"number":52,"description":"And User Enters Patient Phone \"+23063458788\"","duration":1193,"startTime":"2023-05-15T23:29:21.406Z[Etc/UTC]","result":"SUCCESS","precondition":false,"level":1},{"number":53,"description":"Then Field validates \"valid\" Patient Phone","duration":2414,"startTime":"2023-05-15T23:29:22.600Z[Etc/UTC]","result":"SUCCESS","precondition":false,"level":1},{"number":54,"description":"And User Enters Patient Email \"pat@gmail.com\"","duration":10030,"startTime":"2023-05-15T23:29:25.015Z[Etc/UTC]","result":"SUCCESS","precondition":false,"level":1},{"number":55,"description":"Then Field validates \"valid\" Patient Email","duration":10037,"startTime":"2023-05-15T23:29:35.046Z[Etc/UTC]","result":"SUCCESS","precondition":false,"level":1},{"number":56,"description":"And User Selects Patient Health Region","duration":237,"startTime":"2023-05-15T23:29:45.083Z[Etc/UTC]","result":"SUCCESS","precondition":false,"level":1},{"number":57,"description":"And User Selects Patient Health District from the drop down","duration":241,"startTime":"2023-05-15T23:29:45.320Z[Etc/UTC]","result":"SUCCESS","precondition":false,"level":1},{"number":58,"description":"And User Enters Patient Date of Birth \"09/02/2019\"","duration":1286,"startTime":"2023-05-15T23:29:45.562Z[Etc/UTC]","result":"SUCCESS","precondition":false,"level":1},{"number":59,"description":"Then Field validates \"valid\" Patient Date Of Birth","duration":1207,"startTime":"2023-05-15T23:29:46.848Z[Etc/UTC]","result":"SUCCESS","precondition":false,"level":1},{"number":60,"description":"When User Enters Patient Date of Birth in future","duration":1197,"startTime":"2023-05-15T23:29:48.056Z[Etc/UTC]","result":"SUCCESS","precondition":false,"level":1},{"number":61,"description":"Then Alert appears if Date is in the Future","duration":1270,"startTime":"2023-05-15T23:29:49.254Z[Etc/UTC]","result":"SUCCESS","precondition":false,"level":1},{"number":62,"description":"When Date of Birth is left blank and Age \"20\" is filled","duration":1336,"startTime":"2023-05-15T23:29:50.525Z[Etc/UTC]","result":"SUCCESS","precondition":false,"level":1},{"number":63,"description":"Then Field generates Date of Birth with correct year for the Age \"20\"","duration":1187,"startTime":"2023-05-15T23:29:51.864Z[Etc/UTC]","result":"SUCCESS","precondition":false,"level":1},{"number":64,"description":"And Alert Appears if Age entered is -1 , 100 and \u003e100","duration":7409,"startTime":"2023-05-15T23:29:53.051Z[Etc/UTC]","result":"SUCCESS","precondition":false,"level":1},{"number":65,"description":"And User Selects Patient Gender","duration":291,"startTime":"2023-05-15T23:30:00.460Z[Etc/UTC]","result":"SUCCESS","precondition":false,"level":1},{"number":66,"description":"And User Selects Patient Education","duration":224,"startTime":"2023-05-15T23:30:00.753Z[Etc/UTC]","result":"SUCCESS","precondition":false,"level":1},{"number":67,"description":"And User Selects Patient Marital Status","duration":240,"startTime":"2023-05-15T23:30:00.978Z[Etc/UTC]","result":"SUCCESS","precondition":false,"level":1},{"number":68,"description":"And User Enters Patient Other Nationality \"American\"","duration":1174,"startTime":"2023-05-15T23:30:01.218Z[Etc/UTC]","result":"SUCCESS","precondition":false,"level":1}]}],"userStory":{"id":"add-order","storyName":"Add Order","path":"openelis/addOrder.feature","type":"feature"},"featureTag":{"name":"Openelis/Add Order","type":"feature","displayName":"Openelis/Add Order"},"title":"Patient Information","description":"","backgroundTitle":"","backgroundDescription":"","tags":[{"name":"order","type":"tag","displayName":"order"}],"startTime":"2023-05-15T23:27:35.599Z[Etc/UTC]","duration":146892,"projectKey":"","isManualTestingUpToDate":false,"dataTable":{"headers":["subjectNumber","nationalId","pLastName","pFirstName","cLastName","cFirstName","cEmail","cPhone","street","commune","town","pPhone","pEmail","dateOfBirth","nationality","age","status"],"rows":[{"values":["202307D9P","201507D35","Aliou","SADIO","musa","mutes","wrongEmail","+23063458788","New York city, street 3334","Grand yoff","Dakar","ff223377","wrongEmail","09/02/dd","American","20","invalid"],"lineNumber":203,"result":"SUCCESS"},{"values":["202307D9P","201507D35","Aliou","SADIO","musa","mutes","contact@gmail.com","+23063458788","New York city, street 3334","Grand yoff","Dakar","+23063458788","pat@gmail.com","09/02/2019","American","20","valid"],"lineNumber":204,"result":"SUCCESS"}],"predefinedRows":true,"scenarioOutline":"When User Expands Patient information form by clicking the + button next to Patient\n\rAnd User Clicks New Patient Button\n\rAnd User Enters Subject Number \"\u003csubjectNumber\u003e\"\n\rAnd User Enters National ID \"\u003cnationalId\u003e\"\n\rAnd User Enters Patient Last Name \"\u003cpLastName\u003e\"\n\rAnd User Enters Patient First Name \"\u003cpFirstName\u003e\"\n\rAnd User Enters Contact Last Name \"\u003ccLastName\u003e\"\n\rAnd User Enters Contact First Name \"\u003ccFirstName\u003e\"\n\rAnd User Enters Contact Email \"\u003ccEmail\u003e\"\n\rThen Field validates \"\u003cstatus\u003e\" Contact Email\n\rAnd User Enters Contact Phone \"\u003ccPhone\u003e\"\n\rAnd User Enters Patient Street \"\u003cstreet\u003e\"\n\rAnd User Enters Patient Commune \"\u003ccommune\u003e\"\n\rAnd User Enters Patient Town \"\u003ctown\u003e\"\n\rAnd User Enters Patient Phone \"\u003cpPhone\u003e\"\n\rThen Field validates \"\u003cstatus\u003e\" Patient Phone\n\rAnd User Enters Patient Email \"\u003cpEmail\u003e\"\n\rThen Field validates \"\u003cstatus\u003e\" Patient Email\n\rAnd User Selects Patient Health Region\n\rAnd User Selects Patient Health District from the drop down\n\rAnd User Enters Patient Date of Birth \"\u003cdateOfBirth\u003e\"\n\rThen Field validates \"\u003cstatus\u003e\" Patient Date Of Birth\n\rWhen User Enters Patient Date of Birth in future\n\rThen Alert appears if Date is in the Future\n\rWhen Date of Birth is left blank and Age \"\u003cage\u003e\" is filled\n\rThen Field generates Date of Birth with correct year for the Age \"\u003cage\u003e\"\n\rAnd Alert Appears if Age entered is -1 , 100 and \u003e100\n\rAnd User Selects Patient Gender\n\rAnd User Selects Patient Education\n\rAnd User Selects Patient Marital Status\n\rAnd User Enters Patient Other Nationality \"\u003cnationality\u003e\"\n\r","dataSetDescriptors":[{"startRow":0,"rowCount":0,"name":"","description":""}]},"manual":false,"testSource":"Cucumber","result":"SUCCESS","scenarioOutline":"When User Expands Patient information form by clicking the + button next to Patient\nAnd User Clicks New Patient Button\nAnd User Enters Subject Number \"\u003csubjectNumber\u003e\"\nAnd User Enters National ID \"\u003cnationalId\u003e\"\nAnd User Enters Patient Last Name \"\u003cpLastName\u003e\"\nAnd User Enters Patient First Name \"\u003cpFirstName\u003e\"\nAnd User Enters Contact Last Name \"\u003ccLastName\u003e\"\nAnd User Enters Contact First Name \"\u003ccFirstName\u003e\"\nAnd User Enters Contact Email \"\u003ccEmail\u003e\"\nThen Field validates \"\u003cstatus\u003e\" Contact Email\nAnd User Enters Contact Phone \"\u003ccPhone\u003e\"\nAnd User Enters Patient Street \"\u003cstreet\u003e\"\nAnd User Enters Patient Commune \"\u003ccommune\u003e\"\nAnd User Enters Patient Town \"\u003ctown\u003e\"\nAnd User Enters Patient Phone \"\u003cpPhone\u003e\"\nThen Field validates \"\u003cstatus\u003e\" Patient Phone\nAnd User Enters Patient Email \"\u003cpEmail\u003e\"\nThen Field validates \"\u003cstatus\u003e\" Patient Email\nAnd User Selects Patient Health Region\nAnd User Selects Patient Health District from the drop down\nAnd User Enters Patient Date of Birth \"\u003cdateOfBirth\u003e\"\nThen Field validates \"\u003cstatus\u003e\" Patient Date Of Birth\nWhen User Enters Patient Date of Birth in future\nThen Alert appears if Date is in the Future\nWhen Date of Birth is left blank and Age \"\u003cage\u003e\" is filled\nThen Field generates Date of Birth with correct year for the Age \"\u003cage\u003e\"\nAnd Alert Appears if Age entered is -1 , 100 and \u003e100\nAnd User Selects Patient Gender\nAnd User Selects Patient Education\nAnd User Selects Patient Marital Status\nAnd User Enters Patient Other Nationality \"\u003cnationality\u003e\""}