{"name":"Order Number","id":"add-order;order-number","testSteps":[{"number":1,"description":"1: Order Number ({accesionNumber\u003d20230000000001290, status\u003dvalid})","duration":20573,"startTime":"2023-03-20T09:21:54.272Z[Etc/UTC]","result":"SUCCESS","precondition":false,"level":0,"lineNumber":17,"children":[{"number":2,"description":"Given User logs in and visits Home page","duration":6084,"startTime":"2023-03-20T09:21:54.740Z[Etc/UTC]","result":"SUCCESS","precondition":false,"level":1},{"number":3,"description":"And User clicks add order and goes to Add order Page","duration":1569,"startTime":"2023-03-20T09:22:00.825Z[Etc/UTC]","result":"SUCCESS","precondition":false,"level":1},{"number":4,"description":"Then Order form should appear","duration":3046,"startTime":"2023-03-20T09:22:02.394Z[Etc/UTC]","result":"SUCCESS","precondition":false,"level":1},{"number":5,"description":"And Remember site and requester checkbox exists","duration":112,"startTime":"2023-03-20T09:22:05.441Z[Etc/UTC]","result":"SUCCESS","precondition":false,"level":1},{"number":6,"description":"When User enters Accesion Number \"20230000000001290\"","duration":4443,"startTime":"2023-03-20T09:22:05.554Z[Etc/UTC]","result":"SUCCESS","precondition":false,"level":1},{"number":7,"description":"Then Validate \"valid\" AccesionNumber Entered \"20230000000001290\"","duration":3532,"startTime":"2023-03-20T09:22:09.998Z[Etc/UTC]","result":"SUCCESS","precondition":false,"level":1},{"number":8,"description":"When User clicks Generate Button","duration":1170,"startTime":"2023-03-20T09:22:13.531Z[Etc/UTC]","result":"SUCCESS","precondition":false,"level":1},{"number":9,"description":"Then Generated Accesion Number should be a digit","duration":60,"startTime":"2023-03-20T09:22:14.702Z[Etc/UTC]","result":"SUCCESS","precondition":false,"level":1}]},{"number":10,"description":"2: Order Number ({accesionNumber\u003dBETA119000047, status\u003dinvalid})","duration":16985,"startTime":"2023-03-20T09:22:14.885Z[Etc/UTC]","result":"SUCCESS","precondition":false,"level":0,"lineNumber":18,"children":[{"number":11,"description":"Given User logs in and visits Home page","duration":5367,"startTime":"2023-03-20T09:22:15.373Z[Etc/UTC]","result":"SUCCESS","precondition":false,"level":1},{"number":12,"description":"And User clicks add order and goes to Add order Page","duration":1447,"startTime":"2023-03-20T09:22:20.741Z[Etc/UTC]","result":"SUCCESS","precondition":false,"level":1},{"number":13,"description":"Then Order form should appear","duration":2913,"startTime":"2023-03-20T09:22:22.189Z[Etc/UTC]","result":"SUCCESS","precondition":false,"level":1},{"number":14,"description":"And Remember site and requester checkbox exists","duration":121,"startTime":"2023-03-20T09:22:25.103Z[Etc/UTC]","result":"SUCCESS","precondition":false,"level":1},{"number":15,"description":"When User enters Accesion Number \"BETA119000047\"","duration":3968,"startTime":"2023-03-20T09:22:25.225Z[Etc/UTC]","result":"SUCCESS","precondition":false,"level":1},{"number":16,"description":"Then Validate \"invalid\" AccesionNumber Entered \"BETA119000047\"","duration":1308,"startTime":"2023-03-20T09:22:29.194Z[Etc/UTC]","result":"SUCCESS","precondition":false,"level":1},{"number":17,"description":"When User clicks Generate Button","duration":1197,"startTime":"2023-03-20T09:22:30.502Z[Etc/UTC]","result":"SUCCESS","precondition":false,"level":1},{"number":18,"description":"Then Generated Accesion Number should be a digit","duration":88,"startTime":"2023-03-20T09:22:31.700Z[Etc/UTC]","result":"SUCCESS","precondition":false,"level":1}]}],"userStory":{"id":"add-order","storyName":"Add Order","path":"openelis/addOrder.feature","type":"feature"},"featureTag":{"name":"Openelis/Add Order","type":"feature","displayName":"Openelis/Add Order"},"title":"Order Number","description":"","backgroundTitle":"","backgroundDescription":"","tags":[{"name":"order","type":"tag","displayName":"order"}],"startTime":"2023-03-20T09:21:54.269Z[Etc/UTC]","duration":37602,"projectKey":"","isManualTestingUpToDate":false,"dataTable":{"headers":["accesionNumber","status"],"rows":[{"values":["20230000000001290","valid"],"lineNumber":17,"result":"SUCCESS"},{"values":["BETA119000047","invalid"],"lineNumber":18,"result":"SUCCESS"}],"predefinedRows":true,"scenarioOutline":"Then Order form should appear\n\rAnd Remember site and requester checkbox exists\n\rWhen User enters Accesion Number \"\u003caccesionNumber\u003e\"\n\rThen Validate \"\u003cstatus\u003e\" AccesionNumber Entered \"\u003caccesionNumber\u003e\"\n\rWhen User clicks Generate Button\n\rThen Generated Accesion Number should be a digit\n\r","dataSetDescriptors":[{"startRow":0,"rowCount":0,"name":"","description":""}]},"manual":false,"testSource":"Cucumber","result":"SUCCESS","scenarioOutline":"Then Order form should appear\nAnd Remember site and requester checkbox exists\nWhen User enters Accesion Number \"\u003caccesionNumber\u003e\"\nThen Validate \"\u003cstatus\u003e\" AccesionNumber Entered \"\u003caccesionNumber\u003e\"\nWhen User clicks Generate Button\nThen Generated Accesion Number should be a digit"}